nobot/__init__.py
nobot/client.py
nobot/fields.py
nobot/models.py
nobot/widgets.py
nobot/templates/captcha/widget.html
nobot/templates/captcha/widget_ajax.html
nobot/templates/captcha/widget_nocaptcha.html
nobot/tests/__init__.py
nobot/tests/settings.py
nobot/tests/test_client.py
nobot-0.7.dist-info/AUTHORS.rst
nobot-0.7.dist-info/LICENSE
nobot-0.7.dist-info/METADATA
nobot-0.7.dist-info/WHEEL
nobot-0.7.dist-info/top_level.txt
nobot-0.7.dist-info/RECORD
