Metadata-Version: 2.1
Name: nobot
Version: 0.7
Summary: Django recaptcha form field/widget app.
Home-page: https://github.com/EnTeQuak/nobot
Author: Christopher Grebs
Author-email: cg@webshox.org
License: BSD
Platform: UNKNOWN
Classifier: Programming Language :: Python
Classifier: License :: OSI Approved :: BSD License
Classifier: Development Status :: 5 - Production/Stable
Classifier: Operating System :: OS Independent
Classifier: Intended Audience :: Developers
Classifier: Topic :: Internet :: WWW/HTTP :: Dynamic Content
Classifier: Programming Language :: Python
Classifier: Programming Language :: Python :: 2
Classifier: Programming Language :: Python :: 2.7
Classifier: Programming Language :: Python :: 3
Classifier: Programming Language :: Python :: 3.6
Classifier: Programming Language :: Python :: 3.7
Classifier: Programming Language :: Python :: 3.8
Classifier: Programming Language :: Python :: Implementation :: PyPy
Classifier: Programming Language :: Python :: Implementation :: CPython
Classifier: Framework :: Django
Requires-Dist: Django (<2.3,>=1.8)
Requires-Dist: requests (>=1.1.0)
Requires-Dist: six (>=1.9.0)
Provides-Extra: tests
Requires-Dist: pytest (>=3.1.2) ; extra == 'tests'
Requires-Dist: pytest-cov (>=2.5.1) ; extra == 'tests'
Requires-Dist: pytest-flake8 ; extra == 'tests'
Requires-Dist: pytest-django (>=3.1.2) ; extra == 'tests'
Requires-Dist: httpretty (>=1.0.2) ; extra == 'tests'
Requires-Dist: mock (>=2.0.0) ; extra == 'tests'
